lds_web/__init__.py
lds_web/versions.py
lds_web/web_client.py
lds_web-1.2.0.dist-info/METADATA
lds_web-1.2.0.dist-info/WHEEL
lds_web-1.2.0.dist-info/top_level.txt
lds_web-1.2.0.dist-info/RECORD
