Metadata-Version: 2.1
Name: lds-web
Version: 1.2.0
Summary: Web浏览器操作辅助
Home-page: https://github.com/ldsxp/lds_web
Download-URL: https://pypi.org/project/lds_web
Author: lds
Author-email: 85176878@qq.com
License: GNU GPL 3
Platform: any
Classifier: Development Status :: 5 - Production/Stable
Classifier: Intended Audience :: Developers
Classifier: License :: OSI Approved :: GNU General Public License (GPL)
Classifier: Operating System :: OS Independent
Classifier: Programming Language :: Python
Classifier: Programming Language :: Python :: 3.6
Requires-Dist: DrissionPage
